ygg-0.1.57.dist-info/licenses/LICENSE
yggdrasil/__init__.py
yggdrasil/version.py
yggdrasil/databricks/__init__.py
yggdrasil/databricks/ai/__init__.py
yggdrasil/databricks/ai/loki.py
yggdrasil/databricks/compute/__init__.py
yggdrasil/databricks/compute/cluster.py
yggdrasil/databricks/compute/execution_context.py
yggdrasil/databricks/compute/remote.py
yggdrasil/databricks/jobs/__init__.py
yggdrasil/databricks/jobs/config.py
yggdrasil/databricks/sql/__init__.py
yggdrasil/databricks/sql/engine.py
yggdrasil/databricks/sql/exceptions.py
yggdrasil/databricks/sql/statement_result.py
yggdrasil/databricks/sql/types.py
yggdrasil/databricks/sql/warehouse.py
yggdrasil/databricks/workspaces/__init__.py
yggdrasil/databricks/workspaces/filesytem.py
yggdrasil/databricks/workspaces/io.py
yggdrasil/databricks/workspaces/path.py
yggdrasil/databricks/workspaces/path_kind.py
yggdrasil/databricks/workspaces/volumes_path.py
yggdrasil/databricks/workspaces/workspace.py
yggdrasil/dataclasses/__init__.py
yggdrasil/dataclasses/dataclass.py
yggdrasil/libs/__init__.py
yggdrasil/libs/databrickslib.py
yggdrasil/libs/pandaslib.py
yggdrasil/libs/polarslib.py
yggdrasil/libs/sparklib.py
yggdrasil/libs/extensions/__init__.py
yggdrasil/libs/extensions/polars_extensions.py
yggdrasil/libs/extensions/spark_extensions.py
yggdrasil/pyutils/__init__.py
yggdrasil/pyutils/callable_serde.py
yggdrasil/pyutils/equality.py
yggdrasil/pyutils/exceptions.py
yggdrasil/pyutils/expiring_dict.py
yggdrasil/pyutils/modules.py
yggdrasil/pyutils/parallel.py
yggdrasil/pyutils/python_env.py
yggdrasil/pyutils/retry.py
yggdrasil/requests/__init__.py
yggdrasil/requests/msal.py
yggdrasil/requests/session.py
yggdrasil/types/__init__.py
yggdrasil/types/file_format.py
yggdrasil/types/python_arrow.py
yggdrasil/types/python_defaults.py
yggdrasil/types/cast/__init__.py
yggdrasil/types/cast/arrow_cast.py
yggdrasil/types/cast/cast_options.py
yggdrasil/types/cast/pandas_cast.py
yggdrasil/types/cast/polars_cast.py
yggdrasil/types/cast/polars_pandas_cast.py
ygg-0.1.57.dist-info/METADATA
ygg-0.1.57.dist-info/WHEEL
ygg-0.1.57.dist-info/entry_points.txt
ygg-0.1.57.dist-info/top_level.txt
ygg-0.1.57.dist-info/RECORD
