Metadata-Version: 2.4
Name: ygg
Version: 0.1.57
Summary: Type-friendly utilities for moving data between Python objects, Arrow, Polars, Pandas, Spark, and Databricks
Author: Yggdrasil contributors
License:                                  Apache License
Project-URL: Homepage, https://github.com/Platob/Yggdrasil
Project-URL: Repository, https://github.com/Platob/Yggdrasil
Project-URL: Documentation, https://github.com/Platob/Yggdrasil/tree/main/python/docs
Keywords: arrow,polars,pandas,spark,databricks,typing,dataclass,serialization
Classifier: Development Status :: 3 - Alpha
Classifier: Programming Language :: Python
Classifier: Programming Language :: Python :: 3
Classifier: Programming Language :: Python :: 3.10
Classifier: Programming Language :: Python :: 3.11
Classifier: Programming Language :: Python :: 3.12
Classifier: Intended Audience :: Developers
Classifier: Intended Audience :: Information Technology
Classifier: Topic :: Software Development :: Libraries
Classifier: Topic :: Scientific/Engineering :: Information Analysis
Classifier: Typing :: Typed
Requires-Python: >=3.10
License-File: LICENSE
Requires-Dist: requests>=2
Requires-Dist: polars>=1.3
Requires-Dist: pandas>=2
Requires-Dist: pyarrow>=20
Requires-Dist: dill>=0.4
Requires-Dist: databricks-sdk>=0.71
Provides-Extra: dev
Requires-Dist: pytest; extra == "dev"
Requires-Dist: pytest-asyncio; extra == "dev"
Requires-Dist: black; extra == "dev"
Requires-Dist: ruff; extra == "dev"
Requires-Dist: mypy; extra == "dev"
Requires-Dist: build; extra == "dev"
Requires-Dist: twine; extra == "dev"
Dynamic: license-file
